public static void main(String[] args) {
    Function<String, String> lambda = new Function<String, String>() {
        @Override
        public String apply(String s) {
            return s.toUpperCase();
        }
    };
    lambda.apply("String");
}

Classfile /home/gardziol/repository/jvm-miscellaneous/target/classes/dev/jgardo/jvm/miscellaneous/lambda/InnerClassExperiment.class
  Last modified 27 wrz 2019; size 892 bytes
  MD5 checksum 2467b89f947583c02ac8a1f1cf0c247c
  Compiled from "InnerClassExperiment.java"
public class dev.jgardo.jvm.miscellaneous.lambda.InnerClassExperiment
  minor version: 0
  major version: 55
  flags: (0x0021) ACC_PUBLIC, ACC_SUPER
  this_class: #6                          // dev/jgardo/jvm/miscellaneous/lambda/InnerClassExperiment
  super_class: #7                         // java/lang/Object
  interfaces: 0, fields: 0, methods: 2, attributes: 3
Constant pool:
   #1 = Methodref          #7.#27         // java/lang/Object."<init>":()V
   #2 = Class              #28            // dev/jgardo/jvm/miscellaneous/lambda/InnerClassExperiment$1
   #3 = Methodref          #2.#27         // dev/jgardo/jvm/miscellaneous/lambda/InnerClassExperiment$1."<init>":()V
   #4 = String             #29            // String
   #5 = InterfaceMethodref #30.#31        // java/util/function/Function.apply:(Ljava/lang/Object;)Ljava/lang/Object;
   #6 = Class              #32            // dev/jgardo/jvm/miscellaneous/lambda/InnerClassExperiment
   #7 = Class              #33            // java/lang/Object
   #8 = Utf8               InnerClasses
   #9 = Utf8               <init>
  #10 = Utf8               ()V
  #11 = Utf8               Code
  #12 = Utf8               LineNumberTable
  #13 = Utf8               LocalVariableTable
  #14 = Utf8               this
  #15 = Utf8               Ldev/jgardo/jvm/miscellaneous/lambda/InnerClassExperiment;
  #16 = Utf8               main
  #17 = Utf8               ([Ljava/lang/String;)V
  #18 = Utf8               args
  #19 = Utf8               [Ljava/lang/String;
  #20 = Utf8               lambda
  #21 = Utf8               Ljava/util/function/Function;
  #22 = Utf8               LocalVariableTypeTable
  #23 = Utf8               Ljava/util/function/Function<Ljava/lang/String;Ljava/lang/String;>;
  #24 = Utf8               SourceFile
  #25 = Utf8               InnerClassExperiment.java
  #26 = Utf8               NestMembers
  #27 = NameAndType        #9:#10         // "<init>":()V
  #28 = Utf8               dev/jgardo/jvm/miscellaneous/lambda/InnerClassExperiment$1
  #29 = Utf8               String
  #30 = Class              #34            // java/util/function/Function
  #31 = NameAndType        #35:#36        // apply:(Ljava/lang/Object;)Ljava/lang/Object;
  #32 = Utf8               dev/jgardo/jvm/miscellaneous/lambda/InnerClassExperiment
  #33 = Utf8               java/lang/Object
  #34 = Utf8               java/util/function/Function
  #35 = Utf8               apply
  #36 = Utf8               (Ljava/lang/Object;)Ljava/lang/Object;
{
  public dev.jgardo.jvm.miscellaneous.lambda.InnerClassExperiment();
    descriptor: ()V
    flags: (0x0001) ACC_PUBLIC
    Code:
      stack=1, locals=1, args_size=1
         0: aload_0
         1: invokespecial #1                  // Method java/lang/Object."<init>":()V
         4: return
      LineNumberTable:
        line 5: 0
      LocalVariableTable:
        Start  Length  Slot  Name   Signature
            0       5     0  this   Ldev/jgardo/jvm/miscellaneous/lambda/InnerClassExperiment;

  public static void main(java.lang.String[]);
    descriptor: ([Ljava/lang/String;)V
    flags: (0x0009) ACC_PUBLIC, ACC_STATIC
    Code:
      stack=2, locals=2, args_size=1
         0: new           #2                  // class dev/jgardo/jvm/miscellaneous/lambda/InnerClassExperiment$1
         3: dup
         4: invokespecial #3                  // Method dev/jgardo/jvm/miscellaneous/lambda/InnerClassExperiment$1."<init>":()V
         7: astore_1
         8: aload_1
         9: ldc           #4                  // String String
        11: invokeinterface #5,  2            // InterfaceMethod java/util/function/Function.apply:(Ljava/lang/Object;)Ljava/lang/Object;
        16: pop
        17: return
      LineNumberTable:
        line 7: 0
        line 13: 8
        line 14: 17
      LocalVariableTable:
        Start  Length  Slot  Name   Signature
            0      18     0  args   [Ljava/lang/String;
            8      10     1 lambda   Ljava/util/function/Function;
      LocalVariableTypeTable:
        Start  Length  Slot  Name   Signature
            8      10     1 lambda   Ljava/util/function/Function<Ljava/lang/String;Ljava/lang/String;>;
}
SourceFile: "InnerClassExperiment.java"
NestMembers:
  dev/jgardo/jvm/miscellaneous/lambda/InnerClassExperiment$1
InnerClasses:
  #2;                                     // class dev/jgardo/jvm/miscellaneous/lambda/InnerClassExperiment$1


Classfile /home/gardziol/repository/jvm-miscellaneous/target/classes/dev/jgardo/jvm/miscellaneous/lambda/InnerClassExperiment$1.class
  Last modified 27 wrz 2019; size 1011 bytes
  MD5 checksum a5178aa72d3aa0c18cd16b9435c9512e
  Compiled from "InnerClassExperiment.java"
class dev.jgardo.jvm.miscellaneous.lambda.InnerClassExperiment$1 extends java.lang.Object implements java.util.function.Function<java.lang.String, java.lang.String>
  minor version: 0
  major version: 55
  flags: (0x0020) ACC_SUPER
  this_class: #5                          // dev/jgardo/jvm/miscellaneous/lambda/InnerClassExperiment$1
  super_class: #6                         // java/lang/Object
  interfaces: 1, fields: 0, methods: 3, attributes: 5
Constant pool:
   #1 = Methodref          #6.#29         // java/lang/Object."<init>":()V
   #2 = Methodref          #3.#30         // java/lang/String.toUpperCase:()Ljava/lang/String;
   #3 = Class              #31            // java/lang/String
   #4 = Methodref          #5.#32         // dev/jgardo/jvm/miscellaneous/lambda/InnerClassExperiment$1.apply:(Ljava/lang/String;)Ljava/lang/String;
   #5 = Class              #33            // dev/jgardo/jvm/miscellaneous/lambda/InnerClassExperiment$1
   #6 = Class              #34            // java/lang/Object
   #7 = Class              #35            // java/util/function/Function
   #8 = Utf8               <init>
   #9 = Utf8               ()V
  #10 = Utf8               Code
  #11 = Utf8               LineNumberTable
  #12 = Utf8               LocalVariableTable
  #13 = Utf8               this
  #14 = Utf8               InnerClasses
  #15 = Utf8               Ldev/jgardo/jvm/miscellaneous/lambda/InnerClassExperiment$1;
  #16 = Utf8               apply
  #17 = Utf8               (Ljava/lang/String;)Ljava/lang/String;
  #18 = Utf8               s
  #19 = Utf8               Ljava/lang/String;
  #20 = Utf8               (Ljava/lang/Object;)Ljava/lang/Object;
  #21 = Utf8               Signature
  #22 = Utf8               Ljava/lang/Object;Ljava/util/function/Function<Ljava/lang/String;Ljava/lang/String;>;
  #23 = Utf8               SourceFile
  #24 = Utf8               InnerClassExperiment.java
  #25 = Utf8               EnclosingMethod
  #26 = Class              #36            // dev/jgardo/jvm/miscellaneous/lambda/InnerClassExperiment
  #27 = NameAndType        #37:#38        // main:([Ljava/lang/String;)V
  #28 = Utf8               NestHost
  #29 = NameAndType        #8:#9          // "<init>":()V
  #30 = NameAndType        #39:#40        // toUpperCase:()Ljava/lang/String;
  #31 = Utf8               java/lang/String
  #32 = NameAndType        #16:#17        // apply:(Ljava/lang/String;)Ljava/lang/String;
  #33 = Utf8               dev/jgardo/jvm/miscellaneous/lambda/InnerClassExperiment$1
  #34 = Utf8               java/lang/Object
  #35 = Utf8               java/util/function/Function
  #36 = Utf8               dev/jgardo/jvm/miscellaneous/lambda/InnerClassExperiment
  #37 = Utf8               main
  #38 = Utf8               ([Ljava/lang/String;)V
  #39 = Utf8               toUpperCase
  #40 = Utf8               ()Ljava/lang/String;
{
  dev.jgardo.jvm.miscellaneous.lambda.InnerClassExperiment$1();
    descriptor: ()V
    flags: (0x0000)
    Code:
      stack=1, locals=1, args_size=1
         0: aload_0
         1: invokespecial #1                  // Method java/lang/Object."<init>":()V
         4: return
      LineNumberTable:
        line 7: 0
      LocalVariableTable:
        Start  Length  Slot  Name   Signature
            0       5     0  this   Ldev/jgardo/jvm/miscellaneous/lambda/InnerClassExperiment$1;

  public java.lang.String apply(java.lang.String);
    descriptor: (Ljava/lang/String;)Ljava/lang/String;
    flags: (0x0001) ACC_PUBLIC
    Code:
      stack=1, locals=2, args_size=2
         0: aload_1
         1: invokevirtual #2                  // Method java/lang/String.toUpperCase:()Ljava/lang/String;
         4: areturn
      LineNumberTable:
        line 10: 0
      LocalVariableTable:
        Start  Length  Slot  Name   Signature
            0       5     0  this   Ldev/jgardo/jvm/miscellaneous/lambda/InnerClassExperiment$1;
            0       5     1     s   Ljava/lang/String;

  public java.lang.Object apply(java.lang.Object);
    descriptor: (Ljava/lang/Object;)Ljava/lang/Object;
    flags: (0x1041) ACC_PUBLIC, ACC_BRIDGE, ACC_SYNTHETIC
    Code:
      stack=2, locals=2, args_size=2
         0: aload_0
         1: aload_1
         2: checkcast     #3                  // class java/lang/String
         5: invokevirtual #4                  // Method apply:(Ljava/lang/String;)Ljava/lang/String;
         8: areturn
      LineNumberTable:
        line 7: 0
      LocalVariableTable:
        Start  Length  Slot  Name   Signature
            0       9     0  this   Ldev/jgardo/jvm/miscellaneous/lambda/InnerClassExperiment$1;
}
Signature: #22                          // Ljava/lang/Object;Ljava/util/function/Function<Ljava/lang/String;Ljava/lang/String;>;
SourceFile: "InnerClassExperiment.java"
EnclosingMethod: #26.#27                // dev.jgardo.jvm.miscellaneous.lambda.InnerClassExperiment.main
NestHost: class dev/jgardo/jvm/miscellaneous/lambda/InnerClassExperiment
InnerClasses:
  #5;                                     // class dev/jgardo/jvm/miscellaneous/lambda/InnerClassExperiment$1